.travis.yml
CHANGELOG
CONTRIBUTORS
LICENSE
MANIFEST.in
README.rst
requirements.txt
setup.py
Flask_Funnel.egg-info/PKG-INFO
Flask_Funnel.egg-info/SOURCES.txt
Flask_Funnel.egg-info/dependency_links.txt
Flask_Funnel.egg-info/not-zip-safe
Flask_Funnel.egg-info/requires.txt
Flask_Funnel.egg-info/top_level.txt
docs/Makefile
docs/conf.py
docs/index.rst
docs/_static/flask-funnel.jpg
docs/_themes/.gitignore
docs/_themes/LICENSE
docs/_themes/README
docs/_themes/flask_theme_support.py
docs/_themes/flask/layout.html
docs/_themes/flask/relations.html
docs/_themes/flask/theme.conf
docs/_themes/flask/static/flasky.css_t
docs/_themes/flask/static/small_flask.css
docs/_themes/flask_small/layout.html
docs/_themes/flask_small/theme.conf
docs/_themes/flask_small/static/flasky.css_t
docs/example/__init__.py
docs/example/main.py
docs/example/main.pyc
docs/example/manage.py
docs/example/static/bundles/tmp/css/1.css.tmp
docs/example/static/coffee/test1.coffee
docs/example/static/coffee/test2.coffee
docs/example/static/css/1.css
docs/example/static/css/2.css
docs/example/static/css/3.css
docs/example/static/css/style.css
docs/example/static/img/blank.png
docs/example/static/less/1.less
docs/example/static/less/1.less.css
docs/example/static/less/2.less
docs/example/static/less/2.less.css
docs/example/static/less/3.less
docs/example/static/less/3.less.css
docs/example/static/scss/test1.scss
docs/example/static/scss/test2.scss
docs/example/static/stylus/1.styl
docs/example/static/stylus/1.styl.css
docs/example/static/stylus/2.styl
docs/example/static/stylus/2.styl.css
docs/example/static/stylus/import.styl
docs/example/templates/base.html
docs/example/templates/example1.html
docs/example/templates/example2.html
docs/example/templates/example3.html
docs/example/templates/example4.html
docs/example/templates/index.html
docs/example/templates/test-suite.html
docs/example/templates/macros/macros.html
flask_funnel/__init__.py
flask_funnel/_version.py
flask_funnel/extensions.py
flask_funnel/main.py
flask_funnel/manager.py
flask_funnel/tests/__init__.py
flask_funnel/tests/test_funnel.py