Metadata-Version: 1.1
Name: Flask-Funnel
Version: 0.1.10
Summary: Asset management for Flask.
Home-page: http://github.com/rehandalal/flask-funnel/
Author: Rehan Dalal
Author-email: rehan@meet-rehan.com
License: BSD
Platform: any
Classifier: Environment :: Web Environment
Classifier: Intended Audience :: Developers
Classifier: License :: OSI Approved :: BSD License
Classifier: Operating System :: OS Independent
Classifier: Programming Language :: Python
Classifier: Topic :: Internet :: WWW/HTTP :: Dynamic Content
Classifier: Topic :: Software Development :: Libraries :: Python Modules
